humemai/__init__.py
humemai/memory.py
humemai/utils.py
humemai/janusgraph/__init__.py
humemai/janusgraph/humemai.py
humemai/janusgraph/agent/__init__.py
humemai/janusgraph/agent/prompt_agent.py
humemai/janusgraph/agent/prompt_chatbot.py
humemai/janusgraph/utils/__init__.py
humemai/janusgraph/utils/docker.py
humemai/prompt/__init__.py
humemai/prompt/prompt.py
humemai/prompt/templates/__init__.py
humemai/prompt/templates/graph2text_with_properties.py
humemai/prompt/templates/graph2text_without_properties.py
humemai/prompt/templates/text2graph_with_properties.py
humemai/prompt/templates/text2graph_without_properties.py
humemai/rdflib/__init__.py
humemai/rdflib/humemai.py
humemai-2.5.4.dist-info/LICENSE
humemai-2.5.4.dist-info/METADATA
humemai-2.5.4.dist-info/WHEEL
humemai-2.5.4.dist-info/top_level.txt
humemai-2.5.4.dist-info/RECORD
